azure_img_utils/__init__.py
azure_img_utils/auth.py
azure_img_utils/azure_image.py
azure_img_utils/cloud_partner.py
azure_img_utils/compute.py
azure_img_utils/exceptions.py
azure_img_utils/filetype.py
azure_img_utils/storage.py
azure_img_utils/cli/__init__.py
azure_img_utils/cli/blob.py
azure_img_utils/cli/cli.py
azure_img_utils/cli/cli_utils.py
azure_img_utils/cli/gallery_image_version.py
azure_img_utils/cli/image.py
azure_img_utils/cli/offer.py
azure_img_utils-2.5.0.dist-info/licenses/LICENSE
azure_img_utils-2.5.0.dist-info/METADATA
azure_img_utils-2.5.0.dist-info/WHEEL
azure_img_utils-2.5.0.dist-info/entry_points.txt
azure_img_utils-2.5.0.dist-info/top_level.txt
azure_img_utils-2.5.0.dist-info/RECORD
