Metadata-Version: 2.4
Name: azure-img-utils
Version: 2.5.0
Summary: Package that provides utilities for handling images in Azure Cloud.
Home-page: https://github.com/SUSE-Enceladus/azure-img-utils
Author: SUSE
Author-email: public-cloud-dev@susecloud.net
License: GPLv3+
Keywords: azure-img-utils azure_img_utils
Classifier: Development Status :: 4 - Beta
Classifier: Environment :: Console
Classifier: Intended Audience :: Developers
Classifier: Topic :: System :: Software Distribution
Classifier: License :: OSI Approved :: GNU General Public License v3 or later (GPLv3+)
Classifier: Natural Language :: English
Classifier: Programming Language :: Python :: 3
Classifier: Programming Language :: Python :: 3.7
Classifier: Programming Language :: Python :: 3.8
Classifier: Programming Language :: Python :: 3.9
Classifier: Programming Language :: Python :: 3.10
Classifier: Programming Language :: Python :: 3.11
Classifier: Programming Language :: Python :: 3.12
Requires-Python: >=3.7
License-File: LICENSE
Requires-Dist: click
Requires-Dist: msal
Requires-Dist: azure-identity
Requires-Dist: azure-mgmt-compute>=26.1.0
Requires-Dist: azure-mgmt-storage
Requires-Dist: azure-storage-blob>=12.0.0
Requires-Dist: requests
Requires-Dist: jmespath
Requires-Dist: pyyaml
Provides-Extra: dev
Requires-Dist: coverage; extra == "dev"
Requires-Dist: flake8; extra == "dev"
Requires-Dist: pytest; extra == "dev"
Requires-Dist: pytest-cov; extra == "dev"
Requires-Dist: bumpversion; extra == "dev"
Provides-Extra: test
Requires-Dist: coverage; extra == "test"
Requires-Dist: flake8; extra == "test"
Requires-Dist: pytest; extra == "test"
Requires-Dist: pytest-cov; extra == "test"
Dynamic: author
Dynamic: author-email
Dynamic: classifier
Dynamic: description
Dynamic: description-content-type
Dynamic: home-page
Dynamic: keywords
Dynamic: license
Dynamic: license-file
Dynamic: provides-extra
Dynamic: requires-dist
Dynamic: requires-python
Dynamic: summary
